{
  "機關資料": {
    "機關代碼": "3.87.59",
    "機關名稱": "臺中市豐原區公所",
    "單位名稱": "農業及建設課",
    "機關地址": "420臺中市豐原區市政路二號",
    "聯絡人": "柯宏明",
    "聯絡電話": "(04)25222106 分機 331",
    "傳真號碼": "(04)25291412"
  },
  "已公告資料": {
    "標案案號": "101063",
    "招標方式": "公開取得報價單或企劃書",
    "決標方式": "參考最有利標精神",
    "新增公告傳輸次數": "01",
    "標案名稱": "豐原區東陽路太坑巷55號聯外產業道路復建工程等5件委託設計監造案",
    "決標資料類別": "決標公告",
    "是否屬共同供應契約採購": "否",
    "是否複數決標": "否",
    "是否共同投標": "否",
    "標的分類": "<勞務類> 8673 綜合工程服務",
    "是否屬統包": "否",
    "是否應依公共工程專業技師簽證規則實施技師簽證": "本案非屬公共工程專業技師簽證規則規定應實施技師簽證之公共工程，無須實施技師簽證。",
    "開標時間": "101/10/25 10:00",
    "採購金額級距": "未達公告金額",
    "預算金額是否公開": "是",
    "預算金額": "578,300元 招標公告刊登之預算金額：605,200元",
    "是否受機關補助": "是",
    "": "1",
    "履約地點": "臺中市(非原住民地區)",
    "履約地點（含地區）": "臺中市－豐原區",
    "是否屬優先採購身心障礙福利機構產品或勞務": "否",
    "是否含特別預算": "否",
    "歸屬計畫類別": "非屬愛台十二項計畫",
    "本案採購契約是否採用主管機關訂定之範本": "是",
    "辦理方式": "自辦"
  },
  "投標廠商": {
    "投標廠商家數": "2",
    "投標廠商": {
      "1_2": {
        "廠商代碼": "12915444",
        "廠商名稱": "陞兆工程顧問有限公司",
        "是否得標": "是",
        "組織型態": "公司登記",
        "廠商資格": "技術顧問公司",
        "廠商地址": "551南投縣名間鄉南雅村員集路101號",
        "廠商電話": "(049)2732716",
        "決標金額": "413,376元",
        "得標廠商國別": "中華民國(ROC)",
        "原產地國別": "中華民國(ROC)",
        "是否為中小企業": "是",
        "履約起迄日期": "101/12/22－102/01/07",
        "雇用員工總人數是否 超過100人": "否"
      },
      "2_16": {
        "廠商代碼": "84401824",
        "廠商名稱": "永嵩工程顧問有限公司",
        "是否得標": "否",
        "組織型態": "公司登記"
      }
    }
  },
  "決標品項": {
    "決標品項數": "1",
    "品項": {
      "1": {
        "品項名稱": "豐原區東陽路太坑巷55號聯外產業道路復建工程等5件委託設計監造案",
        "是否以單價及預估需 求數量之乘積決定最 低標": "否",
        "得標廠商": {
          "1_5": {
            "得標廠商": "陞兆工程顧問有限公司",
            "預估需求數量": "1",
            "決標金額": "413,376元",
            "底價金額": "418,909元"
          }
        },
        "未得標廠商": {
          "1_10": {
            "未得標廠商": "永嵩工程顧問有限公司",
            "是否合格": "是",
            "未得標原因": "資格、規格合於招標文件但非最有利標或最優勝廠商"
          }
        }
      }
    }
  },
  "決標資料": {
    "決標公告序號": "001",
    "決標日期": "101/12/18",
    "決標公告日期": "101/12/25",
    "是否刊登公報": "是",
    "底價金額": "418,909元",
    "底價金額是否公開": "是",
    "總決標金額": "413,376元",
    "總決標金額是否公開": "是",
    "契約是否訂有依物價指數調整價金規定": "否",
    "未列物價調整規定說明": "勞務案",
    "履約執行機關": "機關代碼：3.87.59機關名稱：臺中市豐原區公所",
    "附加說明": ""
  },
  "url": "http://web.pcc.gov.tw/tps/main/pms/tps/atm/atmAwardAction.do?newEdit=false&searchMode=common&method=inquiryForPublic&pkAtmMain=50861177&tenderCaseNo=101063"
}