{
  "機關資料": {
    "機關代碼": "3.79.66",
    "機關名稱": "臺北市政府觀光傳播局",
    "單位名稱": "媒體出版科",
    "機關地址": "110臺北市信義區市府路1號4樓中央區觀光傳播局",
    "聯絡人": "黃慈萱",
    "聯絡電話": "(02)27208889 分機 7565",
    "傳真號碼": "(02)27205909"
  },
  "已公告資料": {
    "標案案號": "c1010113",
    "招標方式": "公開招標",
    "決標方式": "最低標",
    "是否依「機關異質採購最低標作業須知」辦理": "否",
    "新增公告傳輸次數": "01",
    "標案名稱": "《貓空──攬翠之旅》摺頁改版印製暨配送案",
    "決標資料類別": "決標公告",
    "是否屬共同供應契約採購": "否",
    "是否複數決標": "否",
    "是否共同投標": "否",
    "標的分類": "<勞務類> 88 農業, 礦業及製造業服務",
    "是否屬統包": "否",
    "是否應依公共工程專業技師簽證規則實施技師簽證": "否",
    "開標時間": "101/10/30 14:00",
    "採購金額級距": "公告金額以上未達查核金額",
    "是否適用條約或協定之採購": "否",
    "預算金額是否公開": "是",
    "預算金額": "650,000元",
    "是否受機關補助": "否",
    "履約地點": "臺北市(非原住民地區)",
    "履約地點（含地區）": "臺北市－全區",
    "是否屬優先採購身心障礙福利機構產品或勞務": "否",
    "是否含特別預算": "否",
    "歸屬計畫類別": "非屬愛台十二項計畫",
    "本案採購契約是否採用主管機關訂定之範本": "是",
    "辦理方式": "自辦"
  },
  "投標廠商": {
    "投標廠商家數": "9",
    "投標廠商": {
      "1": {
        "廠商代碼": "81152744",
        "廠商名稱": "卡登實業股份有限公司",
        "是否得標": "否",
        "組織型態": "公司登記"
      },
      "2": {
        "廠商代碼": "16458019",
        "廠商名稱": "鑫鍠企業股份有限公司",
        "是否得標": "否",
        "組織型態": "公司登記"
      },
      "3": {
        "廠商代碼": "75981785",
        "廠商名稱": "千大彩色電子掃描製版股份有限公司",
        "是否得標": "否",
        "組織型態": "公司登記"
      },
      "4": {
        "廠商代碼": "27492339",
        "廠商名稱": "鴻譽彩色印刷有限公司",
        "是否得標": "是",
        "組織型態": "公司登記",
        "廠商資格": "其他",
        "廠商地址": "235新北市中和區福祥里福祥路66號8樓",
        "廠商電話": "(02)82423166",
        "決標金額": "420,350元",
        "得標廠商國別": "中華民國(ROC)",
        "原產地國別": "中華民國(ROC)",
        "是否為中小企業": "是",
        "履約起迄日期": "101/10/30－101/12/31",
        "雇用員工總人數是否 超過100人": "否"
      },
      "5": {
        "廠商代碼": "86730744",
        "廠商名稱": "承漢印刷有限公司",
        "是否得標": "否",
        "組織型態": "公司登記"
      },
      "6": {
        "廠商代碼": "15820097",
        "廠商名稱": "沈氏藝術印刷股份有限公司",
        "是否得標": "否",
        "組織型態": "公司登記"
      },
      "7": {
        "廠商代碼": "24477546",
        "廠商名稱": "撰思文創事業有限公司",
        "是否得標": "否",
        "組織型態": "公司登記"
      },
      "8": {
        "廠商代碼": "22753209",
        "廠商名稱": "錦林印刷有限公司",
        "是否得標": "否",
        "組織型態": "公司登記"
      },
      "9": {
        "廠商代碼": "53689169",
        "廠商名稱": "鴻葵國際有限公司",
        "是否得標": "否",
        "組織型態": "公司登記"
      }
    }
  },
  "決標品項": {
    "決標品項數": "1",
    "品項": {
      "1": {
        "品項名稱": "《貓空──攬翠之旅》摺頁改版印製暨配送案",
        "是否以單價及預估需 求數量之乘積決定最 低標": "否",
        "得標廠商": {
          "1": {
            "得標廠商": "鴻譽彩色印刷有限公司",
            "預估需求數量": "1",
            "決標金額": "420,350元",
            "底價金額": "617,500元"
          }
        },
        "未得標廠商": {
          "1": {
            "未得標廠商": "卡登實業股份有限公司",
            "是否合格": "否",
            "未得標原因": "價格文件未附或不符合規定",
            "標價偏低理由": ""
          },
          "2": {
            "未得標廠商": "鑫鍠企業股份有限公司",
            "是否合格": "是",
            "標價金額": "448,800元",
            "未得標原因": "資格、規格合於招標文件但非最低(高)標",
            "標價偏低理由": ""
          },
          "3": {
            "未得標廠商": "千大彩色電子掃描製版股份有限公司",
            "是否合格": "是",
            "標價金額": "423,800元",
            "未得標原因": "資格、規格合於招標文件但非最低(高)標",
            "標價偏低理由": ""
          },
          "4": {
            "未得標廠商": "承漢印刷有限公司",
            "是否合格": "是",
            "標價金額": "445,428元",
            "未得標原因": "資格、規格合於招標文件但非最低(高)標",
            "標價偏低理由": ""
          },
          "5": {
            "未得標廠商": "沈氏藝術印刷股份有限公司",
            "是否合格": "是",
            "標價金額": "484,000元",
            "未得標原因": "資格、規格合於招標文件但非最低(高)標",
            "標價偏低理由": ""
          },
          "6": {
            "未得標廠商": "撰思文創事業有限公司",
            "是否合格": "是",
            "標價金額": "578,600元",
            "未得標原因": "資格、規格合於招標文件但非最低(高)標",
            "標價偏低理由": ""
          },
          "7": {
            "未得標廠商": "錦林印刷有限公司",
            "是否合格": "是",
            "標價金額": "448,040元",
            "未得標原因": "資格、規格合於招標文件但非最低(高)標",
            "標價偏低理由": ""
          },
          "8": {
            "未得標廠商": "鴻葵國際有限公司",
            "是否合格": "否",
            "未得標原因": "價格文件未附或不符合規定",
            "標價偏低理由": ""
          }
        }
      }
    }
  },
  "決標資料": {
    "決標公告序號": "001",
    "決標日期": "101/10/30",
    "決標公告日期": "101/11/07",
    "是否刊登公報": "是",
    "底價金額": "617,500元",
    "底價金額是否公開": "是",
    "總決標金額": "420,350元",
    "總決標金額是否公開": "是",
    "契約是否訂有依物價指數調整價金規定": "否",
    "未列物價調整規定說明": "勞務案",
    "履約執行機關": "機關代碼：3.79.66機關名稱：臺北市政府觀光傳播局",
    "附加說明": "1.本案計有9家廠商投標。資格審查結果，「卡登實業股份有限公司」因未檢附投標書，依投標須知第42點（六）1及第57點（六）1之規定為無效標，「鴻葵國際有限公司」因投標書未能辨識標價，依投標須知第57點（四）2（6）之規定為無效標，其餘7家廠商之投標文件均符合招標文件規定，為合格廠商。2.續辦合格廠商比價結果：以「鴻譽彩色印刷有限公司」報價最低，且低於核定底價80%，然未低於「各有效標廠商總標價平均值之80%」，依「政府採購法第58條處理總標價低於底價80%案件之執行程序」項次2照價決標予最低標廠商，經主持人當場依政府採購法第52條第1項第1款規定宣布決標。"
  },
  "url": "http://web.pcc.gov.tw/tps/main/pms/tps/atm/atmAwardAction.do?newEdit=false&searchMode=common&method=inquiryForPublic&pkAtmMain=50813789&tenderCaseNo=c1010113"
}