{
  "機關資料": {
    "機關代碼": "3.76.58.32",
    "機關名稱": "新竹市文化局",
    "單位名稱": "新竹市文化局",
    "機關地址": "30003新竹市北區東大路二段15巷1號",
    "聯絡人": "李方宸",
    "聯絡電話": "(03)5420121 分機 313",
    "傳真號碼": "(03)5338012"
  },
  "已公告資料": {
    "標案案號": "101003",
    "招標方式": "公開取得報價單或企劃書",
    "決標方式": "最低標",
    "是否依「機關異質採購最低標作業須知」辦理": "否",
    "新增公告傳輸次數": "01",
    "標案名稱": "「新竹市100年度樹石花卉展成果專輯印刷採購案」",
    "決標資料類別": "定期彙送",
    "是否屬共同供應契約採購": "否",
    "是否複數決標": "否",
    "是否共同投標": "否",
    "標的分類": "<勞務類> 96 娛樂,文化,體育服務",
    "是否屬統包": "否",
    "是否應依公共工程專業技師簽證規則實施技師簽證": "否",
    "開標時間": "101/02/21 10:00",
    "採購金額級距": "未達公告金額",
    "預算金額是否公開": "",
    "預算金額": "240,000元",
    "是否受機關補助": "否",
    "履約地點": "新竹市(非原住民地區)",
    "履約地點（含地區）": "新竹市",
    "是否屬優先採購身心障礙福利機構產品或勞務": "否",
    "是否含特別預算": "否",
    "歸屬計畫類別": "非屬愛台十二項計畫",
    "本案採購契約是否採用主管機關訂定之範本": "是",
    "辦理方式": "自辦"
  },
  "投標廠商": {
    "投標廠商家數": "9",
    "投標廠商": {
      "1": {
        "廠商代碼": "89751314",
        "廠商名稱": "上校基業有限公司",
        "是否得標": "是",
        "組織型態": "公司登記",
        "廠商資格": "其他",
        "廠商地址": "801高雄市前金區文武2街210號10樓之1",
        "廠商電話": "(07)3116011",
        "決標金額": "172,500元",
        "得標廠商國別": "中華民國(ROC)",
        "原產地國別": "中華民國(ROC)",
        "是否為中小企業": "是",
        "履約起迄日期": "101/02/21－101/03/20",
        "雇用員工總人數是否 超過100人": "否"
      },
      "2": {
        "廠商代碼": "89915288",
        "廠商名稱": "龍讚裝訂股份有限公司",
        "是否得標": "否",
        "組織型態": "公司登記"
      },
      "3": {
        "廠商代碼": "84116785",
        "廠商名稱": "信可印刷有限公司",
        "是否得標": "否",
        "組織型態": "公司登記"
      },
      "4": {
        "廠商代碼": "22812827",
        "廠商名稱": "立誠印刷股份有限公司",
        "是否得標": "否",
        "組織型態": "公司登記"
      },
      "5": {
        "廠商代碼": "75346624",
        "廠商名稱": "南光堂印刷所有限公司",
        "是否得標": "否",
        "組織型態": "公司登記"
      },
      "6": {
        "廠商代碼": "15864572",
        "廠商名稱": "中益彩色製版印刷有限公司",
        "是否得標": "否",
        "組織型態": "公司登記"
      },
      "7": {
        "廠商代碼": "23276036",
        "廠商名稱": "宏國印刷事業股份有限公司",
        "是否得標": "否",
        "組織型態": "公司登記"
      },
      "8": {
        "廠商代碼": "45064181",
        "廠商名稱": "上宜行印刷文具有限公司",
        "是否得標": "否",
        "組織型態": "公司登記"
      },
      "9": {
        "廠商代碼": "22334488",
        "廠商名稱": "啟耀印刷事業有限公司",
        "是否得標": "否",
        "組織型態": "公司登記"
      }
    }
  },
  "決標品項": {
    "決標品項數": "1",
    "品項": {
      "1": {
        "品項名稱": "「新竹市100年度樹石花卉展成果專輯印刷採購案」",
        "是否以單價及預估需 求數量之乘積決定最 低標": "",
        "得標廠商": {
          "1": {
            "得標廠商": "上校基業有限公司",
            "預估需求數量": "1",
            "決標金額": "172,500元",
            "底價金額": "220,000元"
          }
        },
        "未得標廠商": {
          "1": {
            "未得標廠商": "龍讚裝訂股份有限公司",
            "是否合格": "是",
            "標價金額": "177,178元",
            "未得標原因": "資格、規格合於招標文件但非最低(高)標",
            "標價偏低理由": ""
          },
          "2": {
            "未得標廠商": "信可印刷有限公司",
            "是否合格": "是",
            "標價金額": "187,200元",
            "未得標原因": "資格、規格合於招標文件但非最低(高)標",
            "標價偏低理由": ""
          },
          "3": {
            "未得標廠商": "立誠印刷股份有限公司",
            "是否合格": "是",
            "標價金額": "180,900元",
            "未得標原因": "資格、規格合於招標文件但非最低(高)標",
            "標價偏低理由": ""
          },
          "4": {
            "未得標廠商": "南光堂印刷所有限公司",
            "是否合格": "是",
            "標價金額": "191,088元",
            "未得標原因": "資格、規格合於招標文件但非最低(高)標",
            "標價偏低理由": ""
          },
          "5": {
            "未得標廠商": "中益彩色製版印刷有限公司",
            "是否合格": "是",
            "標價金額": "178,320元",
            "未得標原因": "資格、規格合於招標文件但非最低(高)標",
            "標價偏低理由": ""
          },
          "6": {
            "未得標廠商": "宏國印刷事業股份有限公司",
            "是否合格": "是",
            "標價金額": "214,130元",
            "未得標原因": "資格、規格合於招標文件但非最低(高)標",
            "標價偏低理由": ""
          },
          "7": {
            "未得標廠商": "上宜行印刷文具有限公司",
            "是否合格": "否",
            "標價金額": "213,900元",
            "未得標原因": "資格文件未附或不符合規定",
            "標價偏低理由": ""
          },
          "8": {
            "未得標廠商": "啟耀印刷事業有限公司",
            "是否合格": "否",
            "未得標原因": "屬採購法第103條第1項不得參加投標或作為決標對象之情形",
            "標價偏低理由": ""
          }
        }
      }
    }
  },
  "決標資料": {
    "決標公告序號": "001",
    "決標日期": "101/02/21",
    "決標公告日期": "101/02/21",
    "是否刊登公報": "否",
    "底價金額": "220,000元",
    "底價金額是否公開": "是",
    "總決標金額": "172,500元",
    "總決標金額是否公開": "是",
    "契約是否訂有依物價指數調整價金規定": "否",
    "未列物價調整規定說明": "勞務案",
    "履約執行機關": "機關代碼：3.76.58.32機關名稱：新竹市文化局",
    "附加說明": "一、本案投標廠商計9家，開標前合格投標廠商計8家，審標結果7家符合招標文件規定，其餘1家不合格。二、其中上校基業有限公司報價新台幣17萬2500元整最低，且在底價22萬元整以內，惟低於底價80%為78.41%，本案經業務單位評估總標價尚屬合理，依政府採購法第58條之執行程序第二項照價決標規定，經主持人當場依政府採購法第52條第1項第1款宣布決標。"
  },
  "url": "http://web.pcc.gov.tw/tps/main/pms/tps/atm/atmAwardAction.do?newEdit=false&searchMode=common&method=inquiryForPublic&pkAtmMain=50624704&tenderCaseNo=101003"
}