{
  "機關資料": {
    "機關代碼": "3.69",
    "機關名稱": "國家通訊傳播委員會",
    "單位名稱": "國家通訊傳播委員會",
    "機關地址": "100臺北市中正區仁愛路1段50號",
    "聯絡人": "劉昔瑄",
    "聯絡電話": "(02)23433717",
    "傳真號碼": "(02)23433701"
  },
  "已公告資料": {
    "標案案號": "NCCN101016-1009",
    "招標方式": "公開招標",
    "決標方式": "最低標",
    "是否依「機關異質採購最低標作業須知」辦理": "否",
    "新增公告傳輸次數": "01",
    "標案名稱": "南區監理處暨屏東高雄電波監測站102-103年度水電空調消防設備維護保養服務購案",
    "決標資料類別": "決標公告",
    "是否屬共同供應契約採購": "否",
    "是否複數決標": "否",
    "是否共同投標": "否",
    "標的分類": "<勞務類> 97 其他服務",
    "是否屬統包": "否",
    "是否應依公共工程專業技師簽證規則實施技師簽證": "否",
    "開標時間": "101/10/25 10:30",
    "採購金額級距": "公告金額以上未達查核金額",
    "是否適用條約或協定之採購": "否",
    "預算金額是否公開": "是",
    "預算金額": "1,560,000元",
    "是否受機關補助": "否",
    "履約地點": "高雄市(非原住民地區)",
    "履約地點（含地區）": "高雄市－新興區,高雄市－大樹區,屏東縣－潮州",
    "是否屬優先採購身心障礙福利機構產品或勞務": "否",
    "是否含特別預算": "否",
    "歸屬計畫類別": "非屬愛台十二項計畫",
    "本案採購契約是否採用主管機關訂定之範本": "是",
    "辦理方式": "自辦"
  },
  "投標廠商": {
    "投標廠商家數": "5",
    "投標廠商": {
      "1_2": {
        "廠商代碼": "14758976",
        "廠商名稱": "一信冷凍空調工程行",
        "是否得標": "是",
        "組織型態": "商業登記",
        "廠商資格": "其他",
        "廠商地址": "621嘉義縣民雄鄉福興村３４１號",
        "廠商電話": "(05)2211383",
        "決標金額": "1,263,058元",
        "得標廠商國別": "中華民國(ROC)",
        "原產地國別": "中華民國(ROC)",
        "是否為中小企業": "是",
        "履約起迄日期": "102/01/01－103/12/31",
        "雇用員工總人數是否 超過100人": "否"
      },
      "2_16": {
        "廠商代碼": "27223882",
        "廠商名稱": "昌儀工程有限公司",
        "是否得標": "否",
        "組織型態": "公司登記"
      },
      "3_21": {
        "廠商代碼": "13184699",
        "廠商名稱": "世盛消防設備檢修有限公司",
        "是否得標": "否",
        "組織型態": "公司登記"
      },
      "4_26": {
        "廠商代碼": "24505536",
        "廠商名稱": "記隆科技有限公司",
        "是否得標": "否",
        "組織型態": "公司登記"
      },
      "5_31": {
        "廠商代碼": "89425655",
        "廠商名稱": "東陽工程有限公司",
        "是否得標": "否",
        "組織型態": "公司登記"
      }
    }
  },
  "決標品項": {
    "決標品項數": "1",
    "品項": {
      "1": {
        "品項名稱": "南區監理處暨屏東高雄電波監測站102-103年度水電空調消防設備維護保養服務購案",
        "是否以單價及預估需 求數量之乘積決定最 低標": "否",
        "得標廠商": {
          "1_5": {
            "得標廠商": "一信冷凍空調工程行",
            "預估需求數量": "1",
            "決標金額": "1,263,058元",
            "底價金額": "1,460,000元"
          }
        },
        "未得標廠商": {
          "1_10": {
            "未得標廠商": "昌儀工程有限公司",
            "是否合格": "是",
            "標價金額": "1,532,278元",
            "未得標原因": "資格、規格合於招標文件但非最低(高)標",
            "標價偏低理由": ""
          },
          "2_16": {
            "未得標廠商": "世盛消防設備檢修有限公司",
            "是否合格": "是",
            "標價金額": "1,320,000元",
            "未得標原因": "資格、規格合於招標文件但非最低(高)標",
            "標價偏低理由": ""
          },
          "3_22": {
            "未得標廠商": "記隆科技有限公司",
            "是否合格": "是",
            "標價金額": "1,296,000元",
            "未得標原因": "資格、規格合於招標文件但非最低(高)標",
            "標價偏低理由": ""
          },
          "4_28": {
            "未得標廠商": "東陽工程有限公司",
            "是否合格": "是",
            "標價金額": "1,349,000元",
            "未得標原因": "資格、規格合於招標文件但非最低(高)標",
            "標價偏低理由": ""
          }
        }
      }
    }
  },
  "決標資料": {
    "決標公告序號": "001",
    "決標日期": "101/10/25",
    "決標公告日期": "101/11/06",
    "是否刊登公報": "是",
    "底價金額": "1,460,000元",
    "底價金額是否公開": "是",
    "總決標金額": "1,263,058元",
    "總決標金額是否公開": "是",
    "契約是否訂有依物價指數調整價金規定": "否",
    "未列物價調整規定說明": "勞務案",
    "履約執行機關": "機關代碼：3.69機關名稱：國家通訊傳播委員會",
    "附加說明": ""
  },
  "url": "http://web.pcc.gov.tw/tps/main/pms/tps/atm/atmAwardAction.do?newEdit=false&searchMode=common&method=inquiryForPublic&pkAtmMain=50812818&tenderCaseNo=NCCN101016-1009"
}