{
  "機關資料": {
    "機關代碼": "3.13.31",
    "機關名稱": "台灣電力股份有限公司",
    "單位名稱": "材料處",
    "機關地址": "100臺北市中正區羅斯福路3段242號8樓",
    "聯絡人": "范姜滿水",
    "聯絡電話": "(02)23666808",
    "傳真號碼": "(02)23684160"
  },
  "採購資料": {
    "標案案號": "0080100016",
    "招標方式": "選擇性招標(建立合格廠商名單後續邀標)",
    "決標方式": "最低標",
    "是否依「機關異質採購最低標作業須知」辦理": "否",
    "是否依據採購法第106條第1項第1款辦理": "否",
    "標案名稱": "15kV交連PE風雨線",
    "決標資料類別": "決標公告",
    "是否屬共同供應契約採購": "否",
    "是否複數決標": "是",
    "選擇性招標建立合格廠商名單標案案號": "K8441200001-2",
    "標的分類": "<財物類> 462 電力傳輸、控制設備及其零件",
    "是否屬統包": "否",
    "是否應依公共工程專業技師簽證規則實施技師簽證": "否",
    "開標時間": "101/10/26 14:00",
    "採購金額級距": "巨額",
    "是否適用條約或協定之採購": "否GPA排除理由:30.電力排除項目HS 8544(非電信電纜部分之電線電纜)。",
    "預算金額是否公開": "是",
    "預算金額": "550,000,000元",
    "是否受機關補助": "否",
    "履約地點": "臺北市(非原住民地區)",
    "履約地點（含地區）": "臺北市－全區",
    "是否屬優先採購身心障礙福利機構產品或勞務": "否",
    "是否含特別預算": "否",
    "歸屬計畫類別": "非屬愛台十二項計畫",
    "本案採購契約是否採用主管機關訂定之範本": "否不採用主管機關訂定之範本之理由：一本公司制定之標準材規辦理.",
    "辦理方式": "自辦"
  },
  "投標廠商": {
    "投標廠商家數": "15",
    "投標廠商": {
      "1": {
        "廠商代碼": "03064800",
        "廠商名稱": "太平洋電線電纜股份有限公司",
        "是否得標": "是",
        "組織型態": "公司登記",
        "廠商資格": "其他",
        "廠商地址": "106臺北市大安區敦化南路2段95號25樓",
        "廠商電話": "(02)66366100",
        "決標金額": "68,400,000元",
        "得標廠商國別": "中華民國(ROC)",
        "原產地國別": "中華民國(ROC)",
        "是否為中小企業": "否，預估分包予中小企業之金額 0 元",
        "履約起迄日期": "101/10/27－103/04/26",
        "雇用員工總人數是否 超過100人": "是",
        "僱用員工總 人數": "968",
        "已僱用原住民 人數": "14",
        "已僱用身心障礙者 人數": "13"
      },
      "2": {
        "廠商代碼": "18523000",
        "廠商名稱": "大東電業廠股份有限公司",
        "是否得標": "是",
        "組織型態": "公司登記",
        "廠商資格": "其他",
        "廠商地址": "326桃園縣楊梅市梅獅路2段349巷3號",
        "廠商電話": "(03)3295101",
        "決標金額": "89,460,000元",
        "得標廠商國別": "中華民國(ROC)",
        "原產地國別": "中華民國(ROC)",
        "是否為中小企業": "否，預估分包予中小企業之金額 0 元",
        "履約起迄日期": "101/10/27－103/04/26",
        "雇用員工總人數是否 超過100人": "是",
        "僱用員工總 人數": "116",
        "已僱用原住民 人數": "1",
        "已僱用身心障礙者 人數": "1"
      },
      "3": {
        "廠商代碼": "72098002",
        "廠商名稱": "華光電線電纜股份有限公司",
        "是否得標": "是",
        "組織型態": "公司登記",
        "廠商資格": "其他",
        "廠商地址": "720臺南市官田區南廍里南廍120號",
        "廠商電話": "(06)5792629",
        "決標金額": "91,200,000元",
        "得標廠商國別": "中華民國(ROC)",
        "原產地國別": "中華民國(ROC)",
        "是否為中小企業": "否，預估分包予中小企業之金額 0 元",
        "履約起迄日期": "101/10/27－103/04/26",
        "雇用員工總人數是否 超過100人": "否"
      },
      "4": {
        "廠商代碼": "35882520",
        "廠商名稱": "中華電線電纜股份有限公司",
        "是否得標": "是",
        "組織型態": "公司登記",
        "廠商資格": "其他",
        "廠商地址": "104臺北市中山區集英里24鄰中山北路3段58號4樓、58號5樓之2",
        "廠商電話": "(02)22021101",
        "決標金額": "68,400,000元",
        "得標廠商國別": "中華民國(ROC)",
        "原產地國別": "中華民國(ROC)",
        "是否為中小企業": "否，預估分包予中小企業之金額 0 元",
        "履約起迄日期": "101/10/27－103/04/26",
        "雇用員工總人數是否 超過100人": "是",
        "僱用員工總 人數": "588",
        "已僱用原住民 人數": "6",
        "已僱用身心障礙者 人數": "7"
      },
      "5": {
        "廠商代碼": "22819700",
        "廠商名稱": "億泰電線電纜股份有限公司",
        "是否得標": "是",
        "組織型態": "公司登記",
        "廠商資格": "其他",
        "廠商地址": "100臺北市中正區仁愛路2段91巷1號1樓",
        "廠商電話": "(02)2819700",
        "決標金額": "134,190,000元",
        "得標廠商國別": "中華民國(ROC)",
        "原產地國別": "中華民國(ROC)",
        "是否為中小企業": "否，預估分包予中小企業之金額 0 元",
        "履約起迄日期": "101/10/27－103/04/26",
        "雇用員工總人數是否 超過100人": "是",
        "僱用員工總 人數": "230",
        "已僱用原住民 人數": "3",
        "已僱用身心障礙者 人數": "3"
      },
      "6": {
        "廠商代碼": "79460007",
        "廠商名稱": "華榮電線電纜股份有限公司",
        "是否得標": "否",
        "組織型態": "公司登記"
      },
      "7": {
        "廠商代碼": "35412204",
        "廠商名稱": "華新麗華股份有限公司",
        "是否得標": "否",
        "組織型態": "公司登記"
      },
      "8": {
        "廠商代碼": "03351015",
        "廠商名稱": "泰電電業股份有限公司",
        "是否得標": "否",
        "組織型態": "公司登記"
      },
      "9": {
        "廠商代碼": "11026506",
        "廠商名稱": "大同股份有限公司",
        "是否得標": "否",
        "組織型態": "公司登記"
      },
      "10": {
        "廠商代碼": "23206102",
        "廠商名稱": "合機電線電纜股份有限公司",
        "是否得標": "否",
        "組織型態": "公司登記"
      },
      "11": {
        "廠商代碼": "34284955",
        "廠商名稱": "台一國際股份有限公司",
        "是否得標": "否",
        "組織型態": "公司登記"
      },
      "12": {
        "廠商代碼": "72104172",
        "廠商名稱": "宗葆電線電纜股份有限公司",
        "是否得標": "否",
        "組織型態": "公司登記"
      },
      "13": {
        "廠商代碼": "68035907",
        "廠商名稱": "大亞電線電纜股份有限公司",
        "是否得標": "否",
        "組織型態": "公司登記"
      },
      "14": {
        "廠商代碼": "64829434",
        "廠商名稱": "大山電線電纜股份有限公司",
        "是否得標": "否",
        "組織型態": "公司登記"
      },
      "15": {
        "廠商代碼": "43125162",
        "廠商名稱": "宏泰電工股份有限公司",
        "是否得標": "否",
        "組織型態": "公司登記"
      }
    }
  },
  "決標品項": {
    "決標品項數": "2",
    "品項": {
      "1": {
        "品項名稱": "0080100016",
        "單位": "件",
        "是否以單價及預估需 求數量之乘積決定最 低標": "是",
        "得標廠商": {
          "1": {
            "得標廠商": "億泰電線電纜股份有限公司",
            "決標單價": "177.5",
            "預估需求數量": "756000",
            "決標金額": "134,190,000元",
            "底價金額": "134,568,000元"
          },
          "2": {
            "得標廠商": "大東電業廠股份有限公司",
            "決標單價": "177.5",
            "預估需求數量": "504000",
            "決標金額": "89,460,000元",
            "底價金額": "89,712,000元"
          }
        },
        "未得標廠商": {
          "1": {
            "未得標廠商": "太平洋電線電纜股份有限公司",
            "是否合格": "是",
            "標價金額": "134,946,000元",
            "未得標原因": "資格、規格合於招標文件但非最低(高)標",
            "標價偏低理由": ""
          },
          "2": {
            "未得標廠商": "華新麗華股份有限公司",
            "是否合格": "是",
            "標價金額": "134,870,400元",
            "未得標原因": "資格、規格合於招標文件但非最低(高)標",
            "標價偏低理由": ""
          },
          "3": {
            "未得標廠商": "大同股份有限公司",
            "是否合格": "是",
            "標價金額": "139,708,800元",
            "未得標原因": "資格、規格合於招標文件但非最低(高)標",
            "標價偏低理由": ""
          },
          "4": {
            "未得標廠商": "台一國際股份有限公司",
            "是否合格": "是",
            "標價金額": "135,172,800元",
            "未得標原因": "資格、規格合於招標文件但非最低(高)標",
            "標價偏低理由": ""
          },
          "5": {
            "未得標廠商": "大亞電線電纜股份有限公司",
            "是否合格": "是",
            "標價金額": "135,324,000元",
            "未得標原因": "資格、規格合於招標文件但非最低(高)標",
            "標價偏低理由": ""
          },
          "6": {
            "未得標廠商": "大山電線電纜股份有限公司",
            "是否合格": "是",
            "標價金額": "142,128,000元",
            "未得標原因": "資格、規格合於招標文件但非最低(高)標",
            "標價偏低理由": ""
          },
          "7": {
            "未得標廠商": "宏泰電工股份有限公司",
            "是否合格": "是",
            "標價金額": "148,176,000元",
            "未得標原因": "資格、規格合於招標文件但非最低(高)標",
            "標價偏低理由": ""
          }
        }
      },
      "2": {
        "品項名稱": "0080100016",
        "單位": "件",
        "是否以單價及預估需 求數量之乘積決定最 低標": "是",
        "得標廠商": {
          "1": {
            "得標廠商": "華光電線電纜股份有限公司",
            "決標單價": "57",
            "預估需求數量": "1600000",
            "決標金額": "91,200,000元",
            "底價金額": "91,520,000元"
          },
          "2": {
            "得標廠商": "太平洋電線電纜股份有限公司",
            "決標單價": "57",
            "預估需求數量": "1200000",
            "決標金額": "68,400,000元",
            "底價金額": "68,640,000元"
          },
          "3": {
            "得標廠商": "中華電線電纜股份有限公司",
            "決標單價": "57",
            "預估需求數量": "1200000",
            "決標金額": "68,400,000元",
            "底價金額": "68,640,000元"
          }
        },
        "未得標廠商": {
          "1": {
            "未得標廠商": "泰電電業股份有限公司",
            "是否合格": "是",
            "標價金額": "92,800,000元",
            "未得標原因": "資格、規格合於招標文件但非最低(高)標",
            "標價偏低理由": ""
          },
          "2": {
            "未得標廠商": "億泰電線電纜股份有限公司",
            "是否合格": "是",
            "標價金額": "104,000,000元",
            "未得標原因": "資格、規格合於招標文件但非最低(高)標",
            "標價偏低理由": ""
          },
          "3": {
            "未得標廠商": "合機電線電纜股份有限公司",
            "是否合格": "是",
            "標價金額": "92,800,000元",
            "未得標原因": "資格、規格合於招標文件但非最低(高)標",
            "標價偏低理由": ""
          },
          "4": {
            "未得標廠商": "華新麗華股份有限公司",
            "是否合格": "是",
            "標價金額": "92,800,000元",
            "未得標原因": "資格、規格合於招標文件但非最低(高)標",
            "標價偏低理由": ""
          },
          "5": {
            "未得標廠商": "宏泰電工股份有限公司",
            "是否合格": "是",
            "標價金額": "102,400,000元",
            "未得標原因": "資格、規格合於招標文件但非最低(高)標",
            "標價偏低理由": ""
          },
          "6": {
            "未得標廠商": "大山電線電纜股份有限公司",
            "是否合格": "是",
            "標價金額": "108,800,000元",
            "未得標原因": "資格、規格合於招標文件但非最低(高)標",
            "標價偏低理由": ""
          },
          "7": {
            "未得標廠商": "大亞電線電纜股份有限公司",
            "是否合格": "是",
            "標價金額": "108,800,000元",
            "未得標原因": "資格、規格合於招標文件但非最低(高)標",
            "標價偏低理由": ""
          },
          "8": {
            "未得標廠商": "宗葆電線電纜股份有限公司",
            "是否合格": "是",
            "標價金額": "99,200,000元",
            "未得標原因": "資格、規格合於招標文件但非最低(高)標",
            "標價偏低理由": ""
          },
          "9": {
            "未得標廠商": "華榮電線電纜股份有限公司",
            "是否合格": "是",
            "標價金額": "107,200,000元",
            "未得標原因": "資格、規格合於招標文件但非最低(高)標",
            "標價偏低理由": ""
          }
        }
      }
    }
  },
  "決標資料": {
    "決標公告序號": "001",
    "決標日期": "101/10/26",
    "決標公告日期": "101/10/31",
    "執行現況": "全案已決標",
    "是否刊登公報": "是",
    "底價金額": "453,080,000元",
    "底價金額是否公開": "是",
    "總決標金額": "451,650,000元",
    "總決標金額是否公開": "是",
    "契約是否訂有依物價指數調整價金規定": "否",
    "未列物價調整規定說明": "財物案",
    "履約執行機關": "機關代碼：3.13.31機關名稱：台灣電力股份有限公司",
    "附加說明": "(1).上述金額全部為未含稅(2).本案共計5個廠商得標,其契約編號如下A項AAC 477MCM:億泰電線電纜公司#008010001601承製數量756,000公尺;大東電業廠公司#008010001602承製數量504,000公尺;B項ACSR AWG#2:華光電線電纜公司#00801000160承製數量1,600,000公尺;太平洋電線電纜公司#008010001604承製數量1200,000公尺;中華電線電纜公司#008010001605承製數量1,200,000公尺."
  },
  "url": "http://web.pcc.gov.tw/tps/main/pms/tps/atm/atmAwardAction.do?newEdit=false&searchMode=common&method=inquiryForPublic&pkAtmMain=50808367&tenderCaseNo=0080100016"
}