{
  "機關資料": {
    "機關代碼": "3.76.43.64",
    "機關名稱": "桃園縣平鎮市公所",
    "單位名稱": "計畫室",
    "機關地址": "324桃園縣平鎮市振興路5號",
    "聯絡人": "行政室",
    "聯絡電話": "(034)572105 分機 2606",
    "傳真號碼": "(034)577043"
  },
  "已公告資料": {
    "標案案號": "1010215A01",
    "招標方式": "公開取得報價單或企劃書",
    "決標方式": "參考最有利標精神",
    "新增公告傳輸次數": "01",
    "標案名稱": "平鎮市公所101年度服務滿意度調查",
    "決標資料類別": "決標公告",
    "是否屬共同供應契約採購": "否",
    "是否複數決標": "否",
    "是否共同投標": "否",
    "標的分類": "<勞務類> 911 政府行政服務",
    "是否屬統包": "否",
    "是否應依公共工程專業技師簽證規則實施技師簽證": "否",
    "開標時間": "101/02/22 09:00",
    "採購金額級距": "未達公告金額",
    "預算金額是否公開": "",
    "預算金額": "250,000元",
    "是否受機關補助": "否",
    "履約地點": "桃園縣(非原住民地區)",
    "履約地點（含地區）": "桃園縣－平鎮",
    "是否屬優先採購身心障礙福利機構產品或勞務": "否",
    "是否含特別預算": "否",
    "歸屬計畫類別": "非屬愛台十二項計畫",
    "本案採購契約是否採用主管機關訂定之範本": "是",
    "辦理方式": "自辦"
  },
  "投標廠商": {
    "投標廠商家數": "6",
    "投標廠商": {
      "1_2": {
        "廠商代碼": "16805741",
        "廠商名稱": "決策調查有限公司",
        "是否得標": "是",
        "組織型態": "公司登記",
        "廠商資格": "其他",
        "廠商地址": "220新北市板橋區文化路一段387巷14號1樓",
        "廠商電話": "(02)66218821",
        "決標金額": "250,000元",
        "得標廠商國別": "中華民國(ROC)",
        "原產地國別": "中華民國(ROC)",
        "是否為中小企業": "是",
        "履約起迄日期": "101/03/03－101/09/30",
        "雇用員工總人數是否 超過100人": "否"
      },
      "2_16": {
        "廠商代碼": "12865514",
        "廠商名稱": "異視行銷市場調查股份有限公司",
        "是否得標": "否",
        "組織型態": "公司登記"
      },
      "3_21": {
        "廠商代碼": "46802708",
        "廠商名稱": "明新科技大學",
        "是否得標": "否",
        "組織型態": "公私立學校"
      },
      "4_26": {
        "廠商代碼": "27772269",
        "廠商名稱": "畢肯市場研究股份有限公司",
        "是否得標": "否",
        "組織型態": "公司登記"
      },
      "5_31": {
        "廠商代碼": "12719668",
        "廠商名稱": "全國公信力民意調查股份有限公司",
        "是否得標": "否",
        "組織型態": "公司登記"
      },
      "6_36": {
        "廠商代碼": "53121236",
        "廠商名稱": "趨勢民意調查股份有限公司",
        "是否得標": "否",
        "組織型態": "公司登記"
      }
    }
  },
  "決標品項": {
    "決標品項數": "1",
    "品項": {
      "1": {
        "品項名稱": "平鎮市公所101年度服務滿意度調查",
        "是否以單價及預估需 求數量之乘積決定最 低標": "",
        "得標廠商": {
          "1_5": {
            "得標廠商": "決策調查有限公司",
            "預估需求數量": "1",
            "決標金額": "250,000元",
            "底價金額": "250,000元"
          }
        },
        "未得標廠商": {
          "1_10": {
            "未得標廠商": "異視行銷市場調查股份有限公司",
            "是否合格": "是",
            "標價金額": "234,100元",
            "未得標原因": "資格、規格合於招標文件但非最有利標或最優勝廠商"
          },
          "2_15": {
            "未得標廠商": "明新科技大學",
            "是否合格": "是",
            "標價金額": "249,000元",
            "未得標原因": "資格、規格合於招標文件但非最有利標或最優勝廠商"
          },
          "3_20": {
            "未得標廠商": "畢肯市場研究股份有限公司",
            "是否合格": "是",
            "標價金額": "247,810元",
            "未得標原因": "資格、規格合於招標文件但非最有利標或最優勝廠商"
          },
          "4_25": {
            "未得標廠商": "全國公信力民意調查股份有限公司",
            "是否合格": "是",
            "標價金額": "249,120元",
            "未得標原因": "資格、規格合於招標文件但非最有利標或最優勝廠商"
          },
          "5_30": {
            "未得標廠商": "趨勢民意調查股份有限公司",
            "是否合格": "是",
            "標價金額": "235,200元",
            "未得標原因": "資格、規格合於招標文件但非最有利標或最優勝廠商"
          }
        }
      }
    }
  },
  "決標資料": {
    "決標公告序號": "001",
    "決標日期": "101/02/23",
    "決標公告日期": "101/02/24",
    "是否刊登公報": "是",
    "底價金額": "250,000元",
    "底價金額是否公開": "是",
    "總決標金額": "250,000元",
    "總決標金額是否公開": "是",
    "契約是否訂有依物價指數調整價金規定": "否",
    "未列物價調整規定說明": "勞務案",
    "履約執行機關": "機關代碼：3.76.43.64機關名稱：桃園縣平鎮市公所",
    "附加說明": ""
  },
  "url": "http://web.pcc.gov.tw/tps/main/pms/tps/atm/atmAwardAction.do?newEdit=false&searchMode=common&method=inquiryForPublic&pkAtmMain=50626571&tenderCaseNo=1010215A01"
}