{
  "機關資料": {
    "機關代碼": "3.9.26.3",
    "機關名稱": "國立成功大學醫學院附設醫院",
    "單位名稱": "資材室",
    "機關地址": "704臺南市北區勝利路138號 資材室 採購組",
    "聯絡人": "林小姐",
    "聯絡電話": "(06)2353535 分機 2850",
    "傳真號碼": "(06)2353762"
  },
  "已公告資料": {
    "標案案號": "T10104",
    "招標方式": "公開招標",
    "決標方式": "最低標",
    "是否依「機關異質採購最低標作業須知」辦理": "否",
    "新增公告傳輸次數": "01",
    "標案名稱": "病歷調閱單等9項",
    "決標資料類別": "決標公告",
    "是否屬共同供應契約採購": "否",
    "是否複數決標": "是",
    "標的分類": "<財物類> 32 紙漿,紙及紙產品;印刷品及相關的商品",
    "是否屬統包": "否",
    "是否應依公共工程專業技師簽證規則實施技師簽證": "否",
    "開標時間": "101/04/12 14:00",
    "採購金額級距": "公告金額以上未達查核金額",
    "是否適用條約或協定之採購": "否",
    "預算金額是否公開": "",
    "預算金額": "2,276,860元",
    "是否受機關補助": "否",
    "履約地點": "臺南市(非原住民地區)",
    "履約地點（含地區）": "臺南市－北區",
    "是否屬優先採購身心障礙福利機構產品或勞務": "是大項分類:印刷 次項分類:專業印刷",
    "是否含特別預算": "否",
    "歸屬計畫類別": "非屬愛台十二項計畫",
    "本案採購契約是否採用主管機關訂定之範本": "是",
    "辦理方式": "自辦"
  },
  "投標廠商": {
    "投標廠商家數": "6",
    "投標廠商": {
      "1": {
        "廠商代碼": "23565036",
        "廠商名稱": "倍旺股份有限公司",
        "是否得標": "是",
        "組織型態": "公司登記",
        "廠商資格": "其他",
        "廠商地址": "710臺南市永康區勝利里勝利街一巷１１弄３８號",
        "廠商電話": "(07)6966310",
        "決標金額": "564,240元",
        "得標廠商國別": "中華民國(ROC)",
        "原產地國別": "中華民國(ROC)",
        "是否為中小企業": "是",
        "履約起迄日期": "101/06/01－102/05/31",
        "雇用員工總人數是否 超過100人": "否"
      },
      "2": {
        "廠商代碼": "69413759",
        "廠商名稱": "嘉記興業有限公司",
        "是否得標": "是",
        "組織型態": "公司登記",
        "廠商資格": "其他",
        "廠商地址": "708臺南市安平區新樂路五二號",
        "廠商電話": "(06)2615821",
        "決標金額": "141,300元",
        "得標廠商國別": "中華民國(ROC)",
        "原產地國別": "中華民國(ROC)",
        "是否為中小企業": "是",
        "履約起迄日期": "101/06/01－102/05/31",
        "雇用員工總人數是否 超過100人": "否"
      },
      "3": {
        "廠商代碼": "96939187",
        "廠商名稱": "元億實業有限公司",
        "是否得標": "是",
        "組織型態": "公司登記",
        "廠商資格": "其他",
        "廠商地址": "103臺北市大同區寧夏路155號9樓",
        "廠商電話": "(02)25571570",
        "決標金額": "83,232元",
        "得標廠商國別": "中華民國(ROC)",
        "原產地國別": "中華民國(ROC)",
        "是否為中小企業": "是",
        "履約起迄日期": "101/06/01－102/05/31",
        "雇用員工總人數是否 超過100人": "否"
      },
      "4": {
        "廠商代碼": "88892673",
        "廠商名稱": "鼎雅打字印刷品社",
        "是否得標": "否",
        "組織型態": "其他"
      },
      "5": {
        "廠商代碼": "38019423",
        "廠商名稱": "永豐紙業股份有限公司",
        "是否得標": "否",
        "組織型態": "公司登記"
      },
      "6": {
        "廠商代碼": "22475727",
        "廠商名稱": "肯達塑膠實業有限公司",
        "是否得標": "是",
        "組織型態": "公司登記",
        "廠商資格": "其他",
        "廠商地址": "412臺中市大里區福德路廿八巷十四號一樓",
        "廠商電話": "(04)24063375",
        "決標金額": "297,840元",
        "得標廠商國別": "中華民國(ROC)",
        "原產地國別": "中華民國(ROC)",
        "是否為中小企業": "是",
        "履約起迄日期": "101/06/10－102/06/09",
        "雇用員工總人數是否 超過100人": "否"
      }
    }
  },
  "決標品項": {
    "決標品項數": "7",
    "品項": {
      "1": {
        "品項名稱": "病歷調閱單",
        "單位": "箱",
        "是否以單價及預估需 求數量之乘積決定最 低標": "",
        "分品項決標": "第1次，日期101/04/12",
        "得標廠商": {
          "1": {
            "得標廠商": "倍旺股份有限公司",
            "預估需求數量": "360",
            "決標金額": "234,000元",
            "底價金額": "234,000元"
          }
        }
      },
      "2": {
        "品項名稱": "黃色報表紙",
        "單位": "箱",
        "是否以單價及預估需 求數量之乘積決定最 低標": "",
        "分品項決標": "第1次，日期101/04/12",
        "得標廠商": {
          "1": {
            "得標廠商": "倍旺股份有限公司",
            "預估需求數量": "132",
            "決標金額": "83,160元",
            "底價金額": "83,160元"
          }
        },
        "未得標廠商": {
          "1": {
            "未得標廠商": "嘉記興業有限公司",
            "是否合格": "是",
            "標價金額": "94,380元",
            "未得標原因": "資格、規格合於招標文件但非最低(高)標",
            "標價偏低理由": ""
          }
        }
      },
      "3": {
        "品項名稱": "橘邊報表紙",
        "單位": "箱",
        "是否以單價及預估需 求數量之乘積決定最 低標": "",
        "分品項決標": "第1次，日期101/04/12",
        "得標廠商": {
          "1": {
            "得標廠商": "倍旺股份有限公司",
            "預估需求數量": "426",
            "決標金額": "247,080元",
            "底價金額": "247,080元"
          }
        },
        "未得標廠商": {
          "1": {
            "未得標廠商": "嘉記興業有限公司",
            "是否合格": "是",
            "標價金額": "293,088元",
            "未得標原因": "資格、規格合於招標文件但非最低(高)標",
            "標價偏低理由": ""
          }
        }
      },
      "4": {
        "品項名稱": "初診3聯式病歷",
        "單位": "份",
        "是否以單價及預估需 求數量之乘積決定最 低標": "",
        "分品項決標": "第1次，日期101/04/12",
        "得標廠商": {
          "1": {
            "得標廠商": "嘉記興業有限公司",
            "預估需求數量": "72000",
            "決標金額": "77,040元",
            "底價金額": "93,600元"
          }
        },
        "未得標廠商": {
          "1": {
            "未得標廠商": "永豐紙業股份有限公司",
            "是否合格": "是",
            "標價金額": "83,520元",
            "未得標原因": "資格、規格合於招標文件但非最低(高)標",
            "標價偏低理由": ""
          },
          "2": {
            "未得標廠商": "鼎雅打字印刷品社",
            "是否合格": "是",
            "標價金額": "93,600元",
            "未得標原因": "資格、規格合於招標文件但非最低(高)標",
            "標價偏低理由": ""
          },
          "3": {
            "未得標廠商": "倍旺股份有限公司",
            "是否合格": "是",
            "標價金額": "86,400元",
            "未得標原因": "資格、規格合於招標文件但非最低(高)標",
            "標價偏低理由": ""
          }
        }
      },
      "5": {
        "品項名稱": "空白病歷夾",
        "單位": "張",
        "是否以單價及預估需 求數量之乘積決定最 低標": "",
        "分品項決標": "第1次，日期101/04/12",
        "得標廠商": {
          "1": {
            "得標廠商": "元億實業有限公司",
            "預估需求數量": "24480",
            "決標金額": "83,232元",
            "底價金額": "93,024元"
          }
        },
        "未得標廠商": {
          "1": {
            "未得標廠商": "永豐紙業股份有限公司",
            "是否合格": "是",
            "標價金額": "87,638.4元",
            "未得標原因": "資格、規格合於招標文件但非最低(高)標",
            "標價偏低理由": ""
          },
          "2": {
            "未得標廠商": "倍旺股份有限公司",
            "是否合格": "是",
            "標價金額": "88,128元",
            "未得標原因": "資格、規格合於招標文件但非最低(高)標",
            "標價偏低理由": ""
          },
          "3": {
            "未得標廠商": "鼎雅打字印刷品社",
            "是否合格": "是",
            "標價金額": "93,024元",
            "未得標原因": "資格、規格合於招標文件但非最低(高)標",
            "標價偏低理由": ""
          }
        }
      },
      "6": {
        "品項名稱": "病歷首頁",
        "單位": "箱",
        "是否以單價及預估需 求數量之乘積決定最 低標": "",
        "分品項決標": "第2次，日期101/04/27",
        "得標廠商": {
          "1": {
            "得標廠商": "嘉記興業有限公司",
            "預估需求數量": "108",
            "決標金額": "64,260元",
            "底價金額": "91,800元"
          }
        },
        "未得標廠商": {
          "1": {
            "未得標廠商": "倍旺股份有限公司",
            "是否合格": "是",
            "標價金額": "91,800元",
            "未得標原因": "資格、規格合於招標文件但非最低(高)標",
            "標價偏低理由": ""
          }
        }
      },
      "7": {
        "品項名稱": "塑膠封套",
        "單位": "份",
        "是否以單價及預估需 求數量之乘積決定最 低標": "",
        "分品項決標": "第3次，日期101/05/04",
        "得標廠商": {
          "1": {
            "得標廠商": "肯達塑膠實業有限公司",
            "預估需求數量": "68000",
            "決標金額": "297,840元",
            "底價金額": "306,000元"
          }
        }
      }
    }
  },
  "決標資料": {
    "決標公告序號": "001",
    "公告更正序號": "002",
    "決標日期": "101/05/04分品項決標：第1次，日期 101/04/12 ;   第2次，日期 101/04/27 ;   第3次，日期 101/05/04 ;  ",
    "原決標公告日期": "101/05/07",
    "決標公告日期": "101/05/08",
    "執行現況": "複數決標案，部分決標",
    "是否刊登公報": "是",
    "底價金額": "1,148,664元",
    "底價金額是否公開": "是",
    "總決標金額": "1,086,612元",
    "總決標金額是否公開": "是",
    "契約是否訂有依物價指數調整價金規定": "否",
    "未列物價調整規定說明": "財物案",
    "履約執行機關": "機關代碼：3.9.26.3機關名稱：國立成功大學醫學院附設醫院",
    "附加說明": "塑膠封套未得標廠商元億實業有限公司而其他廢標品項續辦"
  },
  "url": "http://web.pcc.gov.tw/tps/main/pms/tps/atm/atmAwardAction.do?newEdit=false&searchMode=common&method=inquiryForPublic&pkAtmMain=50677491&tenderCaseNo=T10104"
}