{
  "機關資料": {
    "機關代碼": "3.76.43.97.84",
    "機關名稱": "桃園縣新屋鄉埔頂國民小學",
    "單位名稱": "桃園縣新屋鄉埔頂國民小學",
    "機關地址": "327桃園縣新屋鄉埔頂村中華南路二段五十號",
    "聯絡人": "范瑞東",
    "聯絡電話": "(03)4772240 分機 510",
    "傳真號碼": "(03)4774037"
  },
  "已公告資料": {
    "標案案號": "VC-10012-1",
    "招標方式": "公開取得報價單或企劃書",
    "決標方式": "最低標",
    "是否依「機關異質採購最低標作業須知」辦理": "否",
    "新增公告傳輸次數": "02",
    "標案名稱": "圍牆整建工程",
    "決標資料類別": "決標公告",
    "是否屬共同供應契約採購": "否",
    "是否複數決標": "否",
    "是否共同投標": "否",
    "標的分類": "<工程類> 5127 教育用建築工程",
    "是否屬統包": "否",
    "是否應依公共工程專業技師簽證規則實施技師簽證": "否",
    "開標時間": "100/12/30 09:00",
    "採購金額級距": "未達公告金額",
    "預算金額是否公開": "",
    "預算金額": "700,000元",
    "是否受機關補助": "否",
    "履約地點": "桃園縣(非原住民地區)",
    "履約地點（含地區）": "桃園縣－新屋",
    "是否屬優先採購身心障礙福利機構產品或勞務": "否",
    "是否含特別預算": "否",
    "歸屬計畫類別": "非屬愛台十二項計畫",
    "本案採購契約是否採用主管機關訂定之範本": "是",
    "是否屬災區重建工程": "否",
    "辦理方式": "自辦"
  },
  "投標廠商": {
    "投標廠商家數": "3",
    "投標廠商": {
      "1": {
        "廠商代碼": "23453356",
        "廠商名稱": "龍城金屬有限公司",
        "是否得標": "是",
        "組織型態": "公司登記",
        "廠商資格": "其他",
        "廠商地址": "110臺北市信義區吳興街106巷9號7樓",
        "廠商電話": "(02)29667227",
        "決標金額": "608,739元",
        "得標廠商國別": "中華民國(ROC)",
        "原產地國別": "中華民國(ROC)",
        "是否為中小企業": "是",
        "履約起迄日期": "101/03/01－101/05/31",
        "雇用員工總人數是否 超過100人": "否"
      },
      "2": {
        "廠商代碼": "28960660",
        "廠商名稱": "北區營造工程有限公司",
        "是否得標": "否",
        "組織型態": "公司登記"
      },
      "3": {
        "廠商代碼": "34763218",
        "廠商名稱": "佑峻土木包工業",
        "是否得標": "否",
        "組織型態": "商業登記"
      }
    }
  },
  "決標品項": {
    "決標品項數": "1",
    "品項": {
      "1": {
        "品項名稱": "圍牆整建工程",
        "是否以單價及預估需 求數量之乘積決定最 低標": "",
        "得標廠商": {
          "1": {
            "得標廠商": "龍城金屬有限公司",
            "預估需求數量": "1",
            "決標金額": "608,739元",
            "底價金額": "630,000元"
          }
        },
        "未得標廠商": {
          "1": {
            "未得標廠商": "北區營造工程有限公司",
            "是否合格": "是",
            "標價金額": "643,000元",
            "未得標原因": "資格、規格合於招標文件但非最低(高)標",
            "標價偏低理由": ""
          },
          "2": {
            "未得標廠商": "佑峻土木包工業",
            "是否合格": "是",
            "標價金額": "669,000元",
            "未得標原因": "資格、規格合於招標文件但非最低(高)標",
            "標價偏低理由": ""
          }
        }
      }
    }
  },
  "決標資料": {
    "決標公告序號": "001",
    "決標日期": "100/12/30",
    "決標公告日期": "101/01/11",
    "是否刊登公報": "是",
    "底價金額": "630,000元",
    "底價金額是否公開": "是",
    "總決標金額": "608,739元",
    "總決標金額是否公開": "是",
    "契約是否訂有依物價指數調整價金規定": "否",
    "未列物價調整規定說明": "工期很短",
    "履約執行機關": "機關代碼：3.76.43.97.84機關名稱：桃園縣新屋鄉埔頂國民小學",
    "附加說明": "以確定開工日前三日完成簽約並於45天內限期完工."
  },
  "url": "http://web.pcc.gov.tw/tps/main/pms/tps/atm/atmAwardAction.do?newEdit=false&searchMode=common&method=inquiryForPublic&pkAtmMain=50599879&tenderCaseNo=VC-10012-1"
}