{
  "機關資料": {
    "機關代碼": "3.27.81",
    "機關名稱": "行政院衛生署臺東醫院",
    "單位名稱": "行政院衛生署臺東醫院",
    "機關地址": "950臺東縣臺東市五權街1號",
    "聯絡人": "採購林素貞規格羅鳳娟",
    "聯絡電話": "(089)324112 分機 210",
    "傳真號碼": "(089)343685"
  },
  "已公告資料": {
    "標案案號": "1010515",
    "招標方式": "公開取得報價單或企劃書",
    "決標方式": "最低標",
    "是否依「機關異質採購最低標作業須知」辦理": "否",
    "新增公告傳輸次數": "02",
    "標案名稱": "指型機3台",
    "決標資料類別": "定期彙送",
    "是否屬共同供應契約採購": "否",
    "是否複數決標": "否",
    "是否共同投標": "否",
    "標的分類": "<財物類> 449 其他特殊用途之機具及其零件",
    "是否屬統包": "否",
    "是否應依公共工程專業技師簽證規則實施技師簽證": "否",
    "開標時間": "101/07/10 10:00",
    "採購金額級距": "未達公告金額",
    "預算金額是否公開": "是",
    "預算金額": "225,000元",
    "是否受機關補助": "否",
    "履約地點": "臺東縣台東市(原住民地區)",
    "履約地點（含地區）": "臺東縣－全區",
    "是否屬優先採購身心障礙福利機構產品或勞務": "否",
    "是否含特別預算": "否",
    "歸屬計畫類別": "非屬愛台十二項計畫",
    "本案採購契約是否採用主管機關訂定之範本": "是",
    "辦理方式": "自辦"
  },
  "投標廠商": {
    "投標廠商家數": "2",
    "投標廠商": {
      "1": {
        "廠商代碼": "89676293",
        "廠商名稱": "卓仕科技股份有限公司",
        "廠商名稱(英)": "Excel Systems Inc.",
        "是否得標": "是",
        "組織型態": "公司登記",
        "廠商資格": "其他",
        "廠商地址": "330桃園縣桃園市福林里福林街29號1樓",
        "廠商地址(英)": "No 29 ,Fu-LinSt,Talllem City,Taiwan,R.O.C",
        "廠商電話": "(03)3677727",
        "決標金額": "172,800元",
        "得標廠商國別": "中華民國(ROC)",
        "原產地國別": "中華民國(ROC)",
        "是否為中小企業": "是",
        "履約起迄日期": "101/07/19－101/08/17",
        "雇用員工總人數是否 超過100人": "否"
      },
      "2": {
        "廠商代碼": "97459328",
        "廠商名稱": "潔訊有限公司",
        "廠商名稱(英)": "Transignal Inc",
        "是否得標": "否",
        "組織型態": "公司登記"
      }
    }
  },
  "決標品項": {
    "決標品項數": "1",
    "品項": {
      "1": {
        "品項名稱": "指型機3台",
        "是否以單價及預估需 求數量之乘積決定最 低標": "否",
        "得標廠商": {
          "1": {
            "得標廠商": "卓仕科技股份有限公司",
            "預估需求數量": "1",
            "決標金額": "172,800元",
            "底價金額": "218,000元"
          }
        },
        "未得標廠商": {
          "1": {
            "未得標廠商": "潔訊有限公司",
            "是否合格": "是",
            "標價金額": "197,940元",
            "未得標原因": "資格、規格合於招標文件但非最低(高)標",
            "標價偏低理由": ""
          }
        }
      }
    }
  },
  "英文公告": {
    "機關名稱": "Taitung Hospital,Department of Health,Executive Yuan,Taiwan,R.O.C",
    "機關地址": "No 1 ,Wu Chuan St,Taitung City,Taiwan,R.O.C",
    "標案名稱": "HandKey",
    "聯絡人": "Sue Jen-Lin",
    "聯絡電話": "886-089-324112 Ext 210",
    "傳真號碼": "886-089-343685",
    "得標廠商1": " ",
    "廠商代碼": "97459328",
    "廠商名稱": "Transignal Inc",
    "廠商地址": "No 29 ,Fu-LinSt,Talllem City,Taiwan,R.O.C",
    "未得標廠商1": " ",
    "附加說明": ""
  },
  "決標資料": {
    "決標公告序號": "001",
    "公告更正序號": "001",
    "決標日期": "101/07/18",
    "原決標公告日期": "101/07/23",
    "決標公告日期": "101/07/24",
    "是否刊登公報": "是",
    "底價金額": "218,000元",
    "底價金額是否公開": "是",
    "總決標金額": "172,800元",
    "總決標金額是否公開": "是",
    "契約是否訂有依物價指數調整價金規定": "否",
    "未列物價調整規定說明": "財物案",
    "履約執行機關": "機關代碼：3.27.81機關名稱：行政院衛生署臺東醫院",
    "附加說明": "本案二家投標，業經資格(含規格)審查均符合招標文件，第1家廠商報價197,940元、第二家廠商報價172,800元，因二家廠商均未派員列席開標，無法進行比(減)價程序，第二家廠商報價已進入底價，但有採購法第58條標價低於底價80%之情形，因廠商未列席開標，依據「政府採購法第58條處理總標價低於底價百分之八十案件」之執行程序第四項第一款，已通知廠商儘速提出說明，針對是否降低品質不能誠信履約之虞，惠請相關科室針對相關資料提出意見，業經內部程序後各單位未提出異議，對廠商提出之說明，顯合理無降低品質，於7/18奉簽核可 後辦理決標。"
  },
  "url": "http://web.pcc.gov.tw/tps/main/pms/tps/atm/atmAwardAction.do?newEdit=false&searchMode=common&method=inquiryForPublic&pkAtmMain=50736038&tenderCaseNo=1010515"
}