{
  "機關資料": {
    "機關代碼": "3.15.5.1",
    "機關名稱": "交通部臺灣區國道高速公路局北區工程處",
    "單位名稱": "交通部臺灣區國道高速公路局北區工程處",
    "機關地址": "114臺北市內湖區成功路2段193巷12號",
    "聯絡人": "林哲民",
    "聯絡電話": "(02)27936555 分機 2903",
    "傳真號碼": "(02)27923267"
  },
  "已公告資料": {
    "標案案號": "100B13P005",
    "招標方式": "公開取得報價單或企劃書",
    "決標方式": "參考最有利標精神",
    "新增公告傳輸次數": "01",
    "公告更正序號": "01",
    "標案名稱": "100年度北工處員工工作外套採購(適合秋冬兩季穿著之外套)",
    "決標資料類別": "決標公告",
    "是否屬共同供應契約採購": "否",
    "是否複數決標": "否",
    "是否共同投標": "否",
    "標的分類": "<財物類> 282 成衣, 毛皮服裝除外",
    "是否屬統包": "否",
    "是否應依公共工程專業技師簽證規則實施技師簽證": "否",
    "開標時間": "100/11/16 10:00",
    "採購金額級距": "未達公告金額",
    "預算金額是否公開": "",
    "預算金額": "882,000元",
    "是否受機關補助": "否",
    "履約地點": "臺北市(非原住民地區)",
    "履約地點（含地區）": "臺北市－內湖區",
    "是否屬優先採購身心障礙福利機構產品或勞務": "否",
    "是否含特別預算": "否",
    "歸屬計畫類別": "非屬愛台十二項計畫",
    "本案採購契約是否採用主管機關訂定之範本": "否不採用主管機關訂定之範本之理由：依機關需求辦理",
    "辦理方式": "自辦"
  },
  "投標廠商": {
    "投標廠商家數": "9",
    "投標廠商": {
      "1_2": {
        "廠商代碼": "23466606",
        "廠商名稱": "大傳育樂用品有限公司",
        "是否得標": "是",
        "組織型態": "公司登記",
        "廠商資格": "其他",
        "廠商地址": "105臺北市松山區臺北市松山區光復北路165巷31號1樓",
        "廠商電話": "(02)27695517",
        "決標金額": "882,000元",
        "得標廠商國別": "中華民國(ROC)",
        "原產地國別": "中華民國(ROC)",
        "是否為中小企業": "是",
        "履約起迄日期": "100/11/17－100/12/26",
        "雇用員工總人數是否 超過100人": "否"
      },
      "2_16": {
        "廠商代碼": "27985262",
        "廠商名稱": "根基事業有限公司",
        "是否得標": "否",
        "組織型態": "公司登記"
      },
      "3_21": {
        "廠商代碼": "30119835",
        "廠商名稱": "漢澤企業社",
        "是否得標": "否",
        "組織型態": "其他"
      },
      "4_26": {
        "廠商代碼": "23148244",
        "廠商名稱": "欣晟運動用品有限公司",
        "是否得標": "否",
        "組織型態": "公司登記"
      },
      "5_31": {
        "廠商代碼": "53368737",
        "廠商名稱": "旭悅服裝有限公司",
        "是否得標": "否",
        "組織型態": "公司登記"
      },
      "6_36": {
        "廠商代碼": "84487060",
        "廠商名稱": "都市藍調有限公司",
        "是否得標": "否",
        "組織型態": "公司登記"
      },
      "7_41": {
        "廠商代碼": "89961509",
        "廠商名稱": "齊高有限公司",
        "是否得標": "否",
        "組織型態": "公司登記"
      },
      "8_46": {
        "廠商代碼": "27528603",
        "廠商名稱": "協泰通用有限公司",
        "是否得標": "否",
        "組織型態": "公司登記"
      },
      "9_51": {
        "廠商代碼": "53034177",
        "廠商名稱": "宏達國際實業有限公司",
        "是否得標": "否",
        "組織型態": "公司登記"
      }
    }
  },
  "決標品項": {
    "決標品項數": "1",
    "品項": {
      "1": {
        "品項名稱": "100年度北工處員工工作外套採購(適合秋冬兩季穿著之外套)",
        "是否以單價及預估需 求數量之乘積決定最 低標": "",
        "得標廠商": {
          "1_5": {
            "得標廠商": "大傳育樂用品有限公司",
            "預估需求數量": "1",
            "決標金額": "882,000元"
          }
        },
        "未得標廠商": {
          "1_9": {
            "未得標廠商": "漢澤企業社",
            "是否合格": "是",
            "未得標原因": "資格、規格合於招標文件但非最有利標或最優勝廠商"
          },
          "2_13": {
            "未得標廠商": "欣晟運動用品有限公司",
            "是否合格": "是",
            "未得標原因": "資格、規格合於招標文件但非最有利標或最優勝廠商"
          },
          "3_17": {
            "未得標廠商": "旭悅服裝有限公司",
            "是否合格": "是",
            "未得標原因": "資格、規格合於招標文件但非最有利標或最優勝廠商"
          },
          "4_21": {
            "未得標廠商": "都市藍調有限公司",
            "是否合格": "是",
            "未得標原因": "資格、規格合於招標文件但非最有利標或最優勝廠商"
          },
          "5_25": {
            "未得標廠商": "齊高有限公司",
            "是否合格": "是",
            "未得標原因": "資格、規格合於招標文件但非最有利標或最優勝廠商"
          },
          "6_29": {
            "未得標廠商": "協泰通用有限公司",
            "是否合格": "是",
            "未得標原因": "資格、規格合於招標文件但非最有利標或最優勝廠商"
          },
          "7_33": {
            "未得標廠商": "宏達國際實業有限公司",
            "是否合格": "是",
            "未得標原因": "資格、規格合於招標文件但非最有利標或最優勝廠商"
          },
          "8_37": {
            "未得標廠商": "根基事業有限公司",
            "是否合格": "是",
            "未得標原因": "資格、規格合於招標文件但非最有利標或最優勝廠商"
          }
        }
      }
    }
  },
  "決標資料": {
    "決標公告序號": "001",
    "公告更正序號": "001",
    "決標日期": "100/11/17",
    "原決標公告日期": "100/11/18",
    "決標公告日期": "101/01/05",
    "是否刊登公報": "是",
    "總決標金額": "882,000元",
    "總決標金額是否公開": "是",
    "契約是否訂有依物價指數調整價金規定": "否",
    "未列物價調整規定說明": "財物案",
    "履約執行機關": "機關代碼：3.15.5.1機關名稱：交通部臺灣區國道高速公路局北區工程處",
    "附加說明": ""
  },
  "url": "http://web.pcc.gov.tw/tps/main/pms/tps/atm/atmAwardAction.do?newEdit=false&searchMode=common&method=inquiryForPublic&pkAtmMain=50543890&tenderCaseNo=100B13P005"
}