{
  "機關資料": {
    "機關代碼": "3.79.62",
    "機關名稱": "臺北大眾捷運股份有限公司",
    "單位名稱": "供應處",
    "機關地址": "104臺北市中山區中山北路2段48巷7號4樓",
    "聯絡人": "車輛處 車輛二廠林耕宇",
    "聯絡電話": "(02)22753520 分機 6282",
    "傳真號碼": "(02)25118971"
  },
  "已公告資料": {
    "標案案號": "C01A04054",
    "招標方式": "公開招標",
    "決標方式": "最低標",
    "是否依「機關異質採購最低標作業須知」辦理": "否",
    "新增公告傳輸次數": "02",
    "標案名稱": "ATP 電源板等3項採購",
    "決標資料類別": "決標公告",
    "是否屬共同供應契約採購": "否",
    "是否複數決標": "否",
    "是否共同投標": "否",
    "標的分類": "<財物類> 462 電力傳輸、控制設備及其零件",
    "是否屬統包": "否",
    "是否應依公共工程專業技師簽證規則實施技師簽證": "否",
    "開標時間": "101/07/12 15:00",
    "採購金額級距": "公告金額以上未達查核金額",
    "是否適用條約或協定之採購": "否",
    "預算金額是否公開": "否預算金額不公開理由：機關認為不宜公開",
    "是否受機關補助": "否",
    "履約地點": "臺北市(非原住民地區)",
    "履約地點（含地區）": "臺北市－全區,新北市－全區",
    "是否屬優先採購身心障礙福利機構產品或勞務": "否",
    "是否含特別預算": "否",
    "歸屬計畫類別": "非屬愛台十二項計畫",
    "本案採購契約是否採用主管機關訂定之範本": "是",
    "辦理方式": "自辦"
  },
  "投標廠商": {
    "投標廠商家數": "2",
    "投標廠商": {
      "1_2": {
        "廠商代碼": "53251504",
        "廠商名稱": "聯準電子股份有限公司",
        "是否得標": "是",
        "組織型態": "公司登記",
        "廠商資格": "其他",
        "廠商地址": "806高雄市前鎮區擴建路1之29號14樓",
        "廠商電話": "(07)8131126",
        "決標金額": "1,707,720元",
        "得標廠商國別": "中華民國(ROC)",
        "原產地國別": "中華民國(ROC)",
        "是否為中小企業": "是",
        "履約起迄日期": "101/07/13－101/12/09",
        "雇用員工總人數是否 超過100人": "否"
      },
      "2_16": {
        "廠商代碼": "86315850",
        "廠商名稱": "東鴻電子股份有限公司",
        "是否得標": "否",
        "組織型態": "公司登記"
      }
    }
  },
  "決標品項": {
    "決標品項數": "1",
    "品項": {
      "1": {
        "品項名稱": "ATP 電源板等3項採購",
        "是否以單價及預估需 求數量之乘積決定最 低標": "否",
        "得標廠商": {
          "1_5": {
            "得標廠商": "聯準電子股份有限公司",
            "預估需求數量": "307",
            "決標金額": "1,707,720元",
            "底價金額": "2,678,855元"
          }
        },
        "未得標廠商": {
          "1_10": {
            "未得標廠商": "東鴻電子股份有限公司",
            "是否合格": "是",
            "標價金額": "2,192,568元",
            "未得標原因": "資格、規格合於招標文件但非最低(高)標",
            "標價偏低理由": ""
          }
        }
      }
    }
  },
  "決標資料": {
    "決標公告序號": "001",
    "公告更正序號": "001",
    "決標日期": "101/07/12",
    "原決標公告日期": "101/07/13",
    "決標公告日期": "101/07/17",
    "是否刊登公報": "是",
    "底價金額": "2,678,855元",
    "底價金額是否公開": "是",
    "總決標金額": "1,707,720元",
    "總決標金額是否公開": "是",
    "契約是否訂有依物價指數調整價金規定": "否",
    "未列物價調整規定說明": "財物案",
    "履約執行機關": "機關代碼：3.79.62機關名稱：臺北大眾捷運股份有限公司",
    "附加說明": "1.本案最低標之總標價低於底價之80％，然未低於「各有效標廠商總標價平均值之80％」，依投標須知第61點第11款第4目規定照價決標予最低標。2.本案履約期限：於決標次日起60日內提供樣品每項提供2片及相關資料予機關測試(樣品數量包含於契約數量內)，經機關通知樣品經測試合格後90日內交清，本決標公告履約期限為預估值。3.本次更正內容：修正未得標廠商資料，其餘不變。"
  },
  "url": "http://web.pcc.gov.tw/tps/main/pms/tps/atm/atmAwardAction.do?newEdit=false&searchMode=common&method=inquiryForPublic&pkAtmMain=50730713&tenderCaseNo=C01A04054"
}