{
  "機關資料": {
    "機關代碼": "3.87.1",
    "機關名稱": "臺中市政府秘書處",
    "單位名稱": "臺中市政府秘書處",
    "機關地址": "407臺中市西屯區臺灣大道三段99號",
    "聯絡人": "建設局第二工務大隊 林義翔",
    "聯絡電話": "(04)22289111 分機 34057",
    "傳真號碼": "(04)22206450"
  },
  "已公告資料": {
    "標案案號": "101071602372",
    "招標方式": "公開招標",
    "決標方式": "最低標",
    "是否依「機關異質採購最低標作業須知」辦理": "否",
    "新增公告傳輸次數": "01",
    "標案名稱": "101年度臺中市新社區中正街(中92線)道路路面災害復建工程",
    "決標資料類別": "決標公告",
    "是否屬共同供應契約採購": "否",
    "是否複數決標": "否",
    "是否共同投標": "否",
    "標的分類": "<工程類> 5139 其他土木工程",
    "是否屬統包": "否",
    "是否應依公共工程專業技師簽證規則實施技師簽證": "否",
    "開標時間": "101/07/27 09:30",
    "採購金額級距": "公告金額以上未達查核金額",
    "是否適用條約或協定之採購": "否",
    "預算金額是否公開": "是",
    "預算金額": "9,515,000元",
    "是否受機關補助": "否",
    "履約地點": "臺中市(非原住民地區)",
    "履約地點（含地區）": "臺中市－新社區",
    "是否屬優先採購身心障礙福利機構產品或勞務": "否",
    "是否含特別預算": "否",
    "歸屬計畫類別": "非屬愛台十二項計畫",
    "本案採購契約是否採用主管機關訂定之範本": "是",
    "是否屬災區重建工程": "否",
    "辦理方式": "代辦洽辦機關代碼：3.87.10洽辦機關名稱：臺中市政府建設局"
  },
  "投標廠商": {
    "投標廠商家數": "5",
    "投標廠商": {
      "1_2": {
        "廠商代碼": "28933566",
        "廠商名稱": "航欣營造股份有限公司",
        "是否得標": "是",
        "組織型態": "公司登記",
        "廠商資格": "營造業   營造業登記證號碼: N00186-000",
        "廠商地址": "439臺中市大安區松雅村大安港路536號1樓",
        "廠商電話": "(04)26860707",
        "決標金額": "5,518,000元",
        "得標廠商國別": "中華民國(ROC)",
        "原產地國別": "中華民國(ROC)",
        "是否為中小企業": "是",
        "履約起迄日期": "101/08/30－101/09/30",
        "雇用員工總人數是否 超過100人": "否"
      },
      "2_16": {
        "廠商代碼": "13041617",
        "廠商名稱": "誠東營造有限公司",
        "是否得標": "否",
        "組織型態": "公司登記"
      },
      "3_21": {
        "廠商代碼": "53381274",
        "廠商名稱": "大順瀝青股份有限公司",
        "是否得標": "否",
        "組織型態": "公司登記"
      },
      "4_26": {
        "廠商代碼": "84160677",
        "廠商名稱": "統勤營造有限公司",
        "是否得標": "否",
        "組織型態": "公司登記"
      },
      "5_31": {
        "廠商代碼": "86681048",
        "廠商名稱": "升鴻營造有限公司",
        "是否得標": "否",
        "組織型態": "公司登記"
      }
    }
  },
  "決標品項": {
    "決標品項數": "1",
    "品項": {
      "1": {
        "品項名稱": "101年度臺中市新社區中正街(中92線)道路路面災害復建工程",
        "是否以單價及預估需 求數量之乘積決定最 低標": "否",
        "得標廠商": {
          "1_5": {
            "得標廠商": "航欣營造股份有限公司",
            "預估需求數量": "1",
            "決標金額": "5,518,000元",
            "底價金額": "9,510,000元"
          }
        },
        "未得標廠商": {
          "1_10": {
            "未得標廠商": "誠東營造有限公司",
            "是否合格": "是",
            "標價金額": "6,326,000元",
            "未得標原因": "資格、規格合於招標文件但非最低(高)標",
            "標價偏低理由": ""
          },
          "2_16": {
            "未得標廠商": "大順瀝青股份有限公司",
            "是否合格": "是",
            "標價金額": "8,087,750元",
            "未得標原因": "資格、規格合於招標文件但非最低(高)標",
            "標價偏低理由": ""
          },
          "3_22": {
            "未得標廠商": "統勤營造有限公司",
            "是否合格": "是",
            "標價金額": "5,937,000元",
            "未得標原因": "資格、規格合於招標文件但非最低(高)標",
            "標價偏低理由": ""
          },
          "4_28": {
            "未得標廠商": "升鴻營造有限公司",
            "是否合格": "是",
            "標價金額": "6,490,000元",
            "未得標原因": "資格、規格合於招標文件但非最低(高)標",
            "標價偏低理由": ""
          }
        }
      }
    }
  },
  "決標資料": {
    "決標公告序號": "001",
    "決標日期": "101/08/20",
    "決標公告日期": "101/08/21",
    "是否刊登公報": "是",
    "底價金額": "9,510,000元",
    "底價金額是否公開": "是",
    "總決標金額": "5,518,000元",
    "總決標金額是否公開": "是",
    "契約是否訂有依物價指數調整價金規定": "否",
    "未列物價調整規定說明": "工期很短",
    "履約執行機關": "機關代碼：3.87.10機關名稱：臺中市政府建設局",
    "附加說明": "壹、本案航欣營造股份有限公司以新台幣5,518,000.00元整得標，總契約預計金額新台幣9,515,000.00元整。"
  },
  "url": "http://web.pcc.gov.tw/tps/main/pms/tps/atm/atmAwardAction.do?newEdit=false&searchMode=common&method=inquiryForPublic&pkAtmMain=50757310&tenderCaseNo=101071602372"
}