{
  "機關資料": {
    "機關代碼": "3.76.55",
    "機關名稱": "花蓮縣政府",
    "單位名稱": "花蓮縣政府建設處水利科",
    "機關地址": "970花蓮縣花蓮市府前路17號",
    "聯絡人": "水利科-鄭慶龍",
    "聯絡電話": "(03)8224127",
    "傳真號碼": "(03)8230643"
  },
  "已公告資料": {
    "標案案號": "SE101041901",
    "招標方式": "公開招標",
    "決標方式": "最低標",
    "是否依「機關異質採購最低標作業須知」辦理": "否",
    "新增公告傳輸次數": "01",
    "標案名稱": "花蓮縣101年度災後復建工程委託設計及監造工作「開口契約」",
    "決標資料類別": "決標公告",
    "是否屬共同供應契約採購": "否",
    "是否複數決標": "否",
    "是否共同投標": "否",
    "標的分類": "<勞務類> 8673 綜合工程服務",
    "是否屬統包": "否",
    "是否應依公共工程專業技師簽證規則實施技師簽證": "否",
    "開標時間": "101/05/01 09:30",
    "採購金額級距": "公告金額以上未達查核金額",
    "是否適用條約或協定之採購": "否",
    "預算金額是否公開": "是",
    "預算金額": "2,805,000元",
    "是否受機關補助": "否",
    "履約地點": "花蓮縣(原住民地區)",
    "履約地點（含地區）": "花蓮縣－全區",
    "是否屬優先採購身心障礙福利機構產品或勞務": "否",
    "是否含特別預算": "否",
    "歸屬計畫類別": "非屬愛台十二項計畫",
    "本案採購契約是否採用主管機關訂定之範本": "是",
    "辦理方式": "自辦"
  },
  "投標廠商": {
    "投標廠商家數": "7",
    "投標廠商": {
      "1_2": {
        "廠商代碼": "",
        "廠商名稱": "鈺霖土木技師事務所",
        "是否得標": "是",
        "組織型態": "自然人",
        "廠商資格": "技師事務所",
        "廠商地址": "428臺中市大雅區",
        "廠商電話": "(0933)19****",
        "決標金額": "1,374,450元",
        "得標廠商國別": "中華民國(ROC)",
        "原產地國別": "中華民國(ROC)",
        "是否為中小企業": "是",
        "履約起迄日期": "101/05/08－102/01/31",
        "雇用員工總人數是否 超過100人": "否"
      },
      "2_16": {
        "廠商代碼": "89499229",
        "廠商名稱": "台典工程顧問股份有限公司",
        "是否得標": "否",
        "組織型態": "公司登記"
      },
      "3_21": {
        "廠商代碼": "12823655",
        "廠商名稱": "皇朝工程顧問股份有限公司",
        "是否得標": "否",
        "組織型態": "公司登記"
      },
      "4_26": {
        "廠商代碼": "29005124",
        "廠商名稱": "巍宏工程技術顧問有限公司",
        "是否得標": "否",
        "組織型態": "公司登記"
      },
      "5_31": {
        "廠商代碼": "53138882",
        "廠商名稱": "欣東宜工程顧問有限公司",
        "是否得標": "否",
        "組織型態": "公司登記"
      },
      "6_36": {
        "廠商代碼": "24236049",
        "廠商名稱": "隆成工程顧問有限公司",
        "是否得標": "否",
        "組織型態": "公司登記"
      },
      "7_41": {
        "廠商代碼": "",
        "廠商名稱": "家明土木技師事務所",
        "是否得標": "否",
        "組織型態": "自然人"
      }
    }
  },
  "決標品項": {
    "決標品項數": "1",
    "品項": {
      "1": {
        "品項名稱": "花蓮縣101年度災後復建工程委託設計及監造工作「開口契約」",
        "是否以單價及預估需 求數量之乘積決定最 低標": "",
        "得標廠商": {
          "1_5": {
            "得標廠商": "鈺霖土木技師事務所",
            "預估需求數量": "1",
            "決標金額": "1,374,450元",
            "底價金額": "2,692,800元"
          }
        },
        "未得標廠商": {
          "1_10": {
            "未得標廠商": "台典工程顧問股份有限公司",
            "是否合格": "是",
            "標價金額": "1,739,100元",
            "未得標原因": "資格、規格合於招標文件但非最低(高)標",
            "標價偏低理由": ""
          },
          "2_16": {
            "未得標廠商": "皇朝工程顧問股份有限公司",
            "是否合格": "是",
            "標價金額": "1,402,500元",
            "未得標原因": "資格、規格合於招標文件但非最低(高)標",
            "標價偏低理由": ""
          },
          "3_22": {
            "未得標廠商": "巍宏工程技術顧問有限公司",
            "是否合格": "是",
            "標價金額": "2,075,700元",
            "未得標原因": "資格、規格合於招標文件但非最低(高)標",
            "標價偏低理由": ""
          },
          "4_28": {
            "未得標廠商": "欣東宜工程顧問有限公司",
            "是否合格": "是",
            "標價金額": "1,626,900元",
            "未得標原因": "資格、規格合於招標文件但非最低(高)標",
            "標價偏低理由": ""
          },
          "5_34": {
            "未得標廠商": "隆成工程顧問有限公司",
            "是否合格": "是",
            "標價金額": "1,907,400元",
            "未得標原因": "資格、規格合於招標文件但非最低(高)標",
            "標價偏低理由": ""
          },
          "6_40": {
            "未得標廠商": "家明土木技師事務所",
            "是否合格": "是",
            "標價金額": "0元",
            "未得標原因": "審標合格但未得標之其他原因 ：標價未依標單規定以中文大寫塡寫",
            "標價偏低理由": ""
          }
        }
      }
    }
  },
  "決標資料": {
    "決標公告序號": "001",
    "決標日期": "101/05/08",
    "決標公告日期": "101/05/25",
    "是否刊登公報": "是",
    "底價金額": "2,692,800元",
    "底價金額是否公開": "是",
    "總決標金額": "1,374,450元",
    "總決標金額是否公開": "是",
    "契約是否訂有依物價指數調整價金規定": "否",
    "未列物價調整規定說明": "勞務案",
    "履約執行機關": "機關代碼：3.76.55機關名稱：花蓮縣政府",
    "附加說明": ""
  },
  "url": "http://web.pcc.gov.tw/tps/main/pms/tps/atm/atmAwardAction.do?newEdit=false&searchMode=common&method=inquiryForPublic&pkAtmMain=50692713&tenderCaseNo=SE101041901"
}